prsw/__init__.py
prsw/api.py
prsw/exceptions.py
prsw/ripe_stat.py
prsw/validators.py
prsw/stat/__init__.py
prsw/stat/abuse_contact_finder.py
prsw/stat/announced_prefixes.py
prsw/stat/asn_neighbours.py
prsw/stat/looking_glass.py
prsw/stat/network_info.py
prsw/stat/ris_peers.py
prsw/stat/routing_history.py
prsw/stat/rpki_validation_status.py
prsw/stat/whats_my_ip.py
prsw-0.3.1.dist-info/LICENSE.txt
prsw-0.3.1.dist-info/METADATA
prsw-0.3.1.dist-info/WHEEL
prsw-0.3.1.dist-info/top_level.txt
prsw-0.3.1.dist-info/RECORD
