Metadata-Version: 2.1
Name: prsw
Version: 0.3.1
Summary: PRSW, the Python RIPE Stat Wrapper, is a python package that simplifies access to the RIPE Stat public data API.
Author: Jonathan P. Voss
Author-email: jvoss@onvox.net
License: Simplified BSD License
Project-URL: Documentation, https://prsw.readthedocs.io/
Project-URL: Issue Tracker, https://github.com/jvoss/prsw/issues
Project-URL: Source Code, https://github.com/jvoss/prsw
Keywords: RIPE RIPEStat api wrapper
Classifier: Environment :: Console
Classifier: Intended Audience :: Developers
Classifier: License :: OSI Approved :: BSD License
Classifier: Natural Language :: English
Classifier: Operating System :: OS Independent
Classifier: Programming Language :: Python
Classifier: Programming Language :: Python :: 3
Classifier: Programming Language :: Python :: 3.7
Classifier: Programming Language :: Python :: 3.8
Classifier: Programming Language :: Python :: 3.9
Classifier: Topic :: Utilities
Requires-Python: ~=3.7
License-File: LICENSE.txt
Requires-Dist: requests (>=2)
Provides-Extra: dev
Requires-Dist: packaging ; extra == 'dev'
Requires-Dist: pre-commit ; extra == 'dev'
Requires-Dist: black ; extra == 'dev'
Requires-Dist: flake8 ; extra == 'dev'
Requires-Dist: pydocstyle ; extra == 'dev'
Requires-Dist: sphinx ; extra == 'dev'
Requires-Dist: sphinx-rtd-theme ; extra == 'dev'
Requires-Dist: pytest (>=2.7.3) ; extra == 'dev'
Provides-Extra: lint
Requires-Dist: black ; extra == 'lint'
Requires-Dist: flake8 ; extra == 'lint'
Requires-Dist: pydocstyle ; extra == 'lint'
Requires-Dist: sphinx ; extra == 'lint'
Requires-Dist: sphinx-rtd-theme ; extra == 'lint'
Provides-Extra: readthedocs
Requires-Dist: sphinx ; extra == 'readthedocs'
Provides-Extra: test
Requires-Dist: pytest (>=2.7.3) ; extra == 'test'
